package com.zd.model.audio;

import java.util.ArrayList;
import java.util.Timer;
import java.util.TimerTask;

import android.database.sqlite.SQLiteDatabase;
import android.graphics.Bitmap;

import com.zd.model.DirectorResult;
import com.zd.model.Result;

public class DirectorArtist extends DirectorResult implements Artist {
	protected volatile boolean A = true;
	protected volatile boolean B = false;
	protected Timer C;
	protected TimerTask D;
	protected ArrayList<Artist.OnArtistUpdateListener> E;

	@Override
	public void a(boolean paramBoolean) {
		// TODO Auto-generated method stub

	}

	@Override
	public void a(boolean paramBoolean,
			OnImageUpdateListener paramOnImageUpdateListener) {
		// TODO Auto-generated method stub

	}

	@Override
	public boolean a(SQLiteDatabase paramSQLiteDatabase) {
		// TODO Auto-generated method stub
		return false;
	}

	@Override
	public Bitmap b(boolean paramBoolean) {
		// TODO Auto-generated method stub
		return null;
	}

	@Override
	public boolean o() {
		// TODO Auto-generated method stub
		return false;
	}

	@Override
	public Bitmap p() {
		// TODO Auto-generated method stub
		return null;
	}

	@Override
	public boolean q() {
		// TODO Auto-generated method stub
		return false;
	}

	@Override
	public boolean r() {
		// TODO Auto-generated method stub
		return false;
	}

	@Override
	public boolean s() {
		// TODO Auto-generated method stub
		return false;
	}

	@Override
	public boolean t() {
		// TODO Auto-generated method stub
		return false;
	}

	@Override
	public String u() {
		// TODO Auto-generated method stub
		return null;
	}

	@Override
	public String v() {
		// TODO Auto-generated method stub
		return null;
	}

	@Override
	public String w() {
		// TODO Auto-generated method stub
		return null;
	}

	@Override
	public boolean x() {
		// TODO Auto-generated method stub
		return false;
	}

	@Override
	public String y() {
		// TODO Auto-generated method stub
		return null;
	}

	@Override
	public String at() {
		// TODO Auto-generated method stub
		return null;
	}

	@Override
	public String au() {
		// TODO Auto-generated method stub
		return null;
	}

	@Override
	public void h() {
		// TODO Auto-generated method stub

	}

	@Override
	public int compareTo(Result another) {
		// TODO Auto-generated method stub
		return 0;
	}

	@Override
	public com.zd.model.Results<Album> A() {
		// TODO Auto-generated method stub
		return null;
	}

	@Override
	public boolean B() {
		// TODO Auto-generated method stub
		return false;
	}

	@Override
	public boolean C() {
		// TODO Auto-generated method stub
		return false;
	}

	@Override
	public boolean D() {
		// TODO Auto-generated method stub
		return false;
	}

	@Override
	public boolean F() {
		// TODO Auto-generated method stub
		return false;
	}

	@Override
	public boolean G() {
		// TODO Auto-generated method stub
		return false;
	}

	@Override
	public boolean H() {
		// TODO Auto-generated method stub
		return false;
	}

	@Override
	public com.zd.model.Results<Song> I() {
		// TODO Auto-generated method stub
		return null;
	}

	@Override
	public boolean J() {
		// TODO Auto-generated method stub
		return false;
	}

	@Override
	public boolean K() {
		// TODO Auto-generated method stub
		return false;
	}

	@Override
	public boolean L() {
		// TODO Auto-generated method stub
		return false;
	}

	@Override
	public com.zd.model.Results<Artist> M() {
		// TODO Auto-generated method stub
		return null;
	}

	@Override
	public void N() {
		// TODO Auto-generated method stub

	}

	@Override
	public void O() {
		// TODO Auto-generated method stub

	}

	@Override
	public void P() {
		// TODO Auto-generated method stub

	}

	@Override
	public void Q() {
		// TODO Auto-generated method stub

	}

	@Override
	public CharSequence R() {
		// TODO Auto-generated method stub
		return null;
	}

	@Override
	public CharSequence S() {
		// TODO Auto-generated method stub
		return null;
	}

	@Override
	public boolean T() {
		// TODO Auto-generated method stub
		return false;
	}

	@Override
	public boolean U() {
		// TODO Auto-generated method stub
		return false;
	}

	@Override
	public com.zd.model.Results<Album> V() {
		// TODO Auto-generated method stub
		return null;
	}

	@Override
	public int W() {
		// TODO Auto-generated method stub
		return 0;
	}

	@Override
	public boolean X() {
		// TODO Auto-generated method stub
		return false;
	}

	@Override
	public boolean Y() {
		// TODO Auto-generated method stub
		return false;
	}

	@Override
	public String Z() {
		// TODO Auto-generated method stub
		return null;
	}

	@Override
	public Album a(int paramInt) {
		// TODO Auto-generated method stub
		return null;
	}

	@Override
	public boolean a(OnArtistSamplerListener paramOnArtistSamplerListener) {
		// TODO Auto-generated method stub
		return false;
	}

	@Override
	public boolean a(OnArtistTopAlbumsListener paramOnArtistTopAlbumsListener) {
		// TODO Auto-generated method stub
		return false;
	}

	@Override
	public boolean a(OnArtistTopTracksListener paramOnArtistTopTracksListener) {
		// TODO Auto-generated method stub
		return false;
	}

	@Override
	public boolean a(OnArtistUpdateListener paramOnArtistUpdateListener) {
		// TODO Auto-generated method stub
		return false;
	}

	@Override
	public boolean a(OnRelatedArtistsListener paramOnRelatedArtistsListener) {
		// TODO Auto-generated method stub
		return false;
	}

	@Override
	public boolean a(String paramString,
			OnArtistUpdateListener paramOnArtistUpdateListener) {
		// TODO Auto-generated method stub
		return false;
	}

	@Override
	public boolean a(boolean paramBoolean, String paramString) {
		// TODO Auto-generated method stub
		return false;
	}

	@Override
	public com.zd.model.Results<Album> aa() {
		// TODO Auto-generated method stub
		return null;
	}

	@Override
	public int ab() {
		// TODO Auto-generated method stub
		return 0;
	}

	@Override
	public boolean ac() {
		// TODO Auto-generated method stub
		return false;
	}

	@Override
	public void ad() {
		// TODO Auto-generated method stub

	}

	@Override
	public void ae() {
		// TODO Auto-generated method stub

	}

	@Override
	public Album b(int paramInt) {
		// TODO Auto-generated method stub
		return null;
	}

	@Override
	public void b(OnArtistSamplerListener paramOnArtistSamplerListener) {
		// TODO Auto-generated method stub

	}

	@Override
	public void b(OnArtistTopAlbumsListener paramOnArtistTopAlbumsListener) {
		// TODO Auto-generated method stub

	}

	@Override
	public void b(OnArtistTopTracksListener paramOnArtistTopTracksListener) {
		// TODO Auto-generated method stub

	}

	@Override
	public void b(OnArtistUpdateListener paramOnArtistUpdateListener) {
		// TODO Auto-generated method stub

	}

	@Override
	public void b(OnRelatedArtistsListener paramOnRelatedArtistsListener) {
		// TODO Auto-generated method stub

	}

	@Override
	public Album f(String paramString) {
		// TODO Auto-generated method stub
		return null;
	}

	@Override
	public void g(String paramString) {
		// TODO Auto-generated method stub

	}

	@Override
	public Album h(String paramString) {
		// TODO Auto-generated method stub
		return null;
	}

	@Override
	public Channel i() {
		// TODO Auto-generated method stub
		return null;
	}

	@Override
	public boolean m() {
		// TODO Auto-generated method stub
		return false;
	}

	@Override
	public boolean n() {
		// TODO Auto-generated method stub
		return false;
	}

	@Override
	public com.zd.model.Results<Song> r_() {
		// TODO Auto-generated method stub
		return null;
	}

	@Override
	public boolean z() {
		// TODO Auto-generated method stub
		return false;
	}

	// @g
	// private Application _context;
	// protected DirectorResults<Album> s;
	// protected volatile boolean t = true;
	// protected volatile boolean u = false;
	// protected Timer v;
	// protected TimerTask w;
	// protected boolean x = true;
	// protected String y;
	// protected DirectorResults<Album> z;
	//
	// public DirectorArtist()
	// {
	// this.H = false;
	// }
	//
	// private boolean a(String paramString)
	// {
	// int i = 0;
	// if (paramString != null)
	// try
	// {
	// if ((paramString.length() != 0) && (this.y != null) && (this.y.length()
	// != 0))
	// {
	// boolean bool = this.y.equalsIgnoreCase(paramString);
	// i = bool;
	// }
	// }
	// catch (Exception localException)
	// {
	// Ln.e(localException);
	// }
	// return i;
	// }
	//
	// public Results<Album> A()
	// {
	// return null;
	// }
	//
	// public boolean B()
	// {
	// return false;
	// }
	//
	// public boolean C()
	// {
	// return false;
	// }
	//
	// public boolean D()
	// {
	// return false;
	// }
	//
	// public boolean F()
	// {
	// return false;
	// }
	//
	// public boolean G()
	// {
	// return false;
	// }
	//
	// public boolean H()
	// {
	// return false;
	// }
	//
	// public Results<Song> I()
	// {
	// return null;
	// }
	//
	// public boolean J()
	// {
	// return false;
	// }
	//
	// public boolean K()
	// {
	// return false;
	// }
	//
	// public boolean L()
	// {
	// return false;
	// }
	//
	// public Results<Artist> M()
	// {
	// return null;
	// }
	//
	// public void N()
	// {
	// }
	//
	// public void O()
	// {
	// }
	//
	// public void P()
	// {
	// }
	//
	// public void Q()
	// {
	// }
	//
	// public CharSequence R()
	// {
	// return null;
	// }
	//
	// public CharSequence S()
	// {
	// return null;
	// }
	//
	// public boolean T()
	// {
	// return this.t;
	// }
	//
	// public boolean U()
	// {
	// return this.u;
	// }
	//
	// public Results<Album> V()
	// {
	// return this.s;
	// }
	//
	// public int W()
	// {
	// int i;
	// if (this.s == null)
	// i = 0;
	// else
	// i = this.s.h();
	// return i;
	// }
	//
	// public boolean X()
	// {
	// return this.A;
	// }
	//
	// public boolean Y()
	// {
	// return this.B;
	// }
	//
	// public String Z()
	// {
	// return this.y;
	// }
	//
	// public Album a(int paramInt)
	// {
	// Album localAlbum;
	// if (this.s == null)
	// localAlbum = null;
	// else
	// localAlbum = (Album)this.s.c(paramInt);
	// return localAlbum;
	// }
	//
	// public void a(DirectorAlbum paramDirectorAlbum)
	// {
	// if (paramDirectorAlbum == null)
	// return;
	// while (true)
	// {
	// try
	// {
	// String str1 = paramDirectorAlbum.at();
	// if ((str1 == null) || (str1.length() == 0) || (f(str1) != null))
	// break;
	// if (this.s != null)
	// continue;
	// this.s = new DirectorResults();
	// this.s.a(false);
	// this.s.b(g());
	// DirectorResults localDirectorResults = this.s;
	// StringBuilder localStringBuilder = new
	// StringBuilder().append(au()).append(" ");
	// if (this._context == null)
	// break label144;
	// str1 = this._context.getString(R.string.albums);
	// localDirectorResults.a(str1);
	// this.s.a(paramDirectorAlbum);
	// }
	// catch (Exception localException)
	// {
	// Ln.e(localException);
	// }
	// break;
	// label144: String str2 = "albums";
	// }
	// }
	//
	// public void a(DirectorAlbum paramDirectorAlbum, String paramString)
	// {
	// if (paramDirectorAlbum == null);
	// while (true)
	// {
	// return;
	// if (paramString != null)
	// {
	// try
	// {
	// if (paramString.length() == 0)
	// continue;
	// String str = paramDirectorAlbum.at();
	// if ((str == null) || (str.length() == 0) || (!a(paramString)) || (h(str)
	// != null))
	// continue;
	// if (this.z == null)
	// {
	// this.z = new DirectorResults();
	// this.z.a(false);
	// this.z.b(true);
	// this.z.a(this.y + " " + this._context.getString(R.string.albums));
	// }
	// this.z.a(paramDirectorAlbum);
	// }
	// catch (Exception localException)
	// {
	// Ln.e(localException);
	// }
	// continue;
	// }
	// }
	// }
	//
	// public void a(DirectorResult paramDirectorResult)
	// {
	// super.a(paramDirectorResult);
	// if (paramDirectorResult != null)
	// try
	// {
	// if ((paramDirectorResult instanceof DirectorArtist))
	// {
	// DirectorResults localDirectorResults =
	// ((DirectorArtist)paramDirectorResult).s;
	// if ((localDirectorResults != null) && (localDirectorResults.h() > 0))
	// this.s = localDirectorResults;
	// }
	// }
	// catch (Exception localException)
	// {
	// Ln.e(localException);
	// }
	// }
	//
	// public boolean a(SQLiteDatabase paramSQLiteDatabase)
	// {
	// return false;
	// }
	//
	// // ERROR //
	// public boolean a(SQLiteDatabase paramSQLiteDatabase, String paramString)
	// {
	// // Byte code:
	// // 0: aload_1
	// // 1: ifnonnull +9 -> 10
	// // 4: iconst_0
	// // 5: istore 4
	// // 7: iload 4
	// // 9: ireturn
	// // 10: aload_0
	// // 11: invokevirtual 131 com/control4/director/audio/DirectorArtist:au
	// ()Ljava/lang/String;
	// // 14: astore 5
	// // 16: aload 5
	// // 18: ifnull +302 -> 320
	// // 21: aload 5
	// // 23: invokevirtual 57 java/lang/String:length ()I
	// // 26: ifeq +294 -> 320
	// // 29: aload_2
	// // 30: ifnull +290 -> 320
	// // 33: aload_2
	// // 34: invokevirtual 57 java/lang/String:length ()I
	// // 37: ifne +6 -> 43
	// // 40: goto +280 -> 320
	// // 43: aload_1
	// // 44: monitorenter
	// // 45: iconst_3
	// // 46: anewarray 53 java/lang/String
	// // 49: astore 4
	// // 51: aload 4
	// // 53: iconst_0
	// // 54: ldc 174
	// // 56: aastore
	// // 57: aload 4
	// // 59: iconst_1
	// // 60: ldc 176
	// // 62: aastore
	// // 63: aload 4
	// // 65: iconst_2
	// // 66: ldc 178
	// // 68: aastore
	// // 69: iconst_2
	// // 70: anewarray 53 java/lang/String
	// // 73: astore_3
	// // 74: aload_3
	// // 75: iconst_0
	// // 76: aload 5
	// // 78: aastore
	// // 79: aload_3
	// // 80: iconst_1
	// // 81: aload_2
	// // 82: aastore
	// // 83: aload_1
	// // 84: ldc 180
	// // 86: aload 4
	// // 88: ldc 182
	// // 90: aload_3
	// // 91: aconst_null
	// // 92: aconst_null
	// // 93: aconst_null
	// // 94: invokevirtual 188 android/database/sqlite/SQLiteDatabase:query
	// (Ljava/lang/String;[Ljava/lang/String;Ljava/lang/String;[Ljava/lang/String;Ljava/lang/String;Ljava/lang/String;Ljava/lang/String;)Landroid/database/Cursor;
	// // 97: astore_3
	// // 98: aload_3
	// // 99: ldc 174
	// // 101: invokeinterface 194 2 0
	// // 106: istore 5
	// // 108: aload_3
	// // 109: ldc 176
	// // 111: invokeinterface 194 2 0
	// // 116: istore 6
	// // 118: aload_3
	// // 119: ldc 178
	// // 121: invokeinterface 194 2 0
	// // 126: istore 4
	// // 128: aload_3
	// // 129: invokeinterface 197 1 0
	// // 134: ifeq +180 -> 314
	// // 137: aload_3
	// // 138: iload 5
	// // 140: invokeinterface 198 2 0
	// // 145: astore 7
	// // 147: aload_3
	// // 148: iload 6
	// // 150: invokeinterface 198 2 0
	// // 155: astore 10
	// // 157: aload_3
	// // 158: iload 4
	// // 160: invokeinterface 198 2 0
	// // 165: astore 9
	// // 167: aload_0
	// // 168: getfield 202 com/control4/director/audio/DirectorArtist:_director
	// Lcom/control4/director/Control4Director;
	// // 171: getfield 208
	// com/control4/director/Control4Director:_albumProvider
	// Lcom/google/inject/aw;
	// // 174: invokeinterface 213 1 0
	// // 179: checkcast 108 com/control4/director/audio/DirectorAlbum
	// // 182: astore 8
	// // 184: aload 7
	// // 186: ifnull +18 -> 204
	// // 189: aload 7
	// // 191: invokevirtual 57 java/lang/String:length ()I
	// // 194: ifle +10 -> 204
	// // 197: aload 8
	// // 199: aload 7
	// // 201: invokevirtual 216 com/control4/director/audio/DirectorAlbum:l
	// (Ljava/lang/String;)V
	// // 204: aload 10
	// // 206: ifnull +18 -> 224
	// // 209: aload 10
	// // 211: invokevirtual 57 java/lang/String:length ()I
	// // 214: ifle +10 -> 224
	// // 217: aload 8
	// // 219: aload 10
	// // 221: invokevirtual 219 com/control4/director/audio/DirectorAlbum:m
	// (Ljava/lang/String;)V
	// // 224: aload 9
	// // 226: ifnull +18 -> 244
	// // 229: aload 9
	// // 231: invokevirtual 57 java/lang/String:length ()I
	// // 234: ifle +10 -> 244
	// // 237: aload 8
	// // 239: aload 9
	// // 241: invokevirtual 222 com/control4/director/audio/DirectorAlbum:n
	// (Ljava/lang/String;)V
	// // 244: aload_0
	// // 245: aload 8
	// // 247: aload_2
	// // 248: invokevirtual 224 com/control4/director/audio/DirectorArtist:a
	// (Lcom/control4/director/audio/DirectorAlbum;Ljava/lang/String;)V
	// // 251: aload_3
	// // 252: invokeinterface 227 1 0
	// // 257: istore 7
	// // 259: iload 7
	// // 261: ifne -124 -> 137
	// // 264: iconst_1
	// // 265: istore 4
	// // 267: aload_3
	// // 268: ifnull +9 -> 277
	// // 271: aload_3
	// // 272: invokeinterface 230 1 0
	// // 277: aload_1
	// // 278: monitorexit
	// // 279: goto -272 -> 7
	// // 282: astore_3
	// // 283: aload_1
	// // 284: monitorexit
	// // 285: aload_3
	// // 286: athrow
	// // 287: astore_3
	// // 288: aload_3
	// // 289: invokestatic 68 roboguice/util/Ln:e (Ljava/lang/Throwable;)I
	// // 292: pop
	// // 293: iconst_0
	// // 294: istore 4
	// // 296: goto -289 -> 7
	// // 299: astore 4
	// // 301: aload_3
	// // 302: ifnull +9 -> 311
	// // 305: aload_3
	// // 306: invokeinterface 230 1 0
	// // 311: aload 4
	// // 313: athrow
	// // 314: iconst_0
	// // 315: istore 4
	// // 317: goto -50 -> 267
	// // 320: iconst_0
	// // 321: istore 4
	// // 323: goto -316 -> 7
	// //
	// // Exception table:
	// // from to target type
	// // 45 128 282 finally
	// // 271 285 282 finally
	// // 305 314 282 finally
	// // 10 45 287 java/lang/Exception
	// // 285 287 287 java/lang/Exception
	// // 128 259 299 finally
	// }
	//
	// public boolean a(Artist.OnArtistSamplerListener
	// paramOnArtistSamplerListener)
	// {
	// return false;
	// }
	//
	// public boolean a(Artist.OnArtistTopAlbumsListener
	// paramOnArtistTopAlbumsListener)
	// {
	// return false;
	// }
	//
	// public boolean a(Artist.OnArtistTopTracksListener
	// paramOnArtistTopTracksListener)
	// {
	// return false;
	// }
	//
	// public boolean a(Artist.OnArtistUpdateListener
	// paramOnArtistUpdateListener)
	// {
	// boolean bool1 = true;
	// try
	// {
	// if (this._director == null)
	// {
	// bool1 = false;
	// break label209;
	// }
	// if (this.u)
	// break label209;
	// if (this._director.G())
	// {
	// bool1 = b(this._director.q());
	// l(false);
	// m(false);
	// if (paramOnArtistUpdateListener == null)
	// break label209;
	// paramOnArtistUpdateListener.a(this);
	// }
	// }
	// catch (Exception i)
	// {
	// Ln.e(localException);
	// m(false);
	// int i = 0;
	// }
	// m(true);
	// Object localObject = au();
	// if ((localObject != null) && (((String)localObject).length() != 0) &&
	// (!((String)localObject).equals("(Empty)")));
	// while (true)
	// {
	// String str2 = ((String)localObject).replaceAll("&", "&amp;");
	// localObject =
	// (GetArtistAlbumsCommand)CommandFactory.GetArtistsAlbumsProvider.a();
	// ((GetArtistAlbumsCommand)localObject).a(str2);
	// ((GetArtistAlbumsCommand)localObject).a("artist", this);
	// if (paramOnArtistUpdateListener != null)
	// ((GetArtistAlbumsCommand)localObject).a("listener",
	// paramOnArtistUpdateListener);
	// ((GetArtistAlbumsCommand)localObject).a("audio-library", f());
	// ((GetArtistAlbumsCommand)localObject).b(this._director.m().r());
	// boolean bool2 = this._director.a((Command)localObject);
	// if (!bool2)
	// m(false);
	// label209: return bool2;
	// String str1 = "";
	// }
	// }
	//
	// public boolean a(Artist.OnRelatedArtistsListener
	// paramOnRelatedArtistsListener)
	// {
	// return false;
	// }
	//
	// public boolean a(String paramString, Artist.OnArtistUpdateListener
	// paramOnArtistUpdateListener)
	// {
	// boolean bool1 = true;
	// try
	// {
	// if (this._director == null)
	// {
	// bool1 = false;
	// break label245;
	// }
	// if (this.B)
	// break label245;
	// if (this._director.G())
	// {
	// bool1 = a(this._director.q(), paramString);
	// n(false);
	// o(false);
	// if (paramOnArtistUpdateListener == null)
	// break label245;
	// paramOnArtistUpdateListener.a(this, paramString);
	// }
	// }
	// catch (Exception i)
	// {
	// Ln.e(localException);
	// o(false);
	// int i = 0;
	// }
	// o(true);
	// ae();
	// this.y = paramString;
	// Object localObject = this.y;
	// if ((localObject != null) && (!((String)localObject).equals("(Empty)")));
	// while (true)
	// {
	// String str2 = ((String)localObject + "|" + au()).replaceAll("&",
	// "&amp;");
	// localObject =
	// (GetArtistGenreAlbumsCommand)CommandFactory.GetArtistsGenreAlbumsProvider.a();
	// ((GetArtistGenreAlbumsCommand)localObject).a(str2);
	// ((GetArtistGenreAlbumsCommand)localObject).a("artist", this);
	// ((GetArtistGenreAlbumsCommand)localObject).a("listener",
	// paramOnArtistUpdateListener);
	// ((GetArtistGenreAlbumsCommand)localObject).a("audio-library", f());
	// ((GetArtistGenreAlbumsCommand)localObject).a("genreId", paramString);
	// ((GetArtistGenreAlbumsCommand)localObject).b(this._director.m().r());
	// boolean bool2 = this._director.a((Command)localObject);
	// if (!bool2)
	// o(false);
	// label245: return bool2;
	// String str1 = "";
	// }
	// }
	//
	// public boolean a(boolean paramBoolean, String paramString)
	// {
	// int k;
	// try
	// {
	// if (this._director == null)
	// {
	// int i = 0;
	// }
	// else
	// {
	// DirectorProject localDirectorProject = this._director.m();
	// int j;
	// if (localDirectorProject == null)
	// {
	// j = 0;
	// }
	// else
	// {
	// Object localObject2 = j.s();
	// if (localObject2 == null)
	// {
	// j = 0;
	// }
	// else
	// {
	// Object localObject1 = ((Room)localObject2).ar();
	// if ((localObject1 != null) && (((AudioQueue)localObject1).c() ==
	// AudioQueue.QueueState.b));
	// localObject1 = new
	// StringBuilder("<param><name>ARTIST</name><value type=\"STRING\"><static>");
	// ((StringBuilder)localObject1).append(au());
	// ((StringBuilder)localObject1).append("</static></value></param>");
	// ((StringBuilder)localObject1).append("<param><name>ROOM_ID</name><value type=\"INTEGER\"><static>");
	// ((StringBuilder)localObject1).append(this._director.m().r());
	// ((StringBuilder)localObject1).append("</static></value></param>");
	// ((StringBuilder)localObject1).append("<param><name>PLAY_NOW</name><value type=\"STRING\"><static>");
	// ((StringBuilder)localObject1).append("1");
	// ((StringBuilder)localObject1).append("</static></value></param>");
	// ((StringBuilder)localObject1).append("<param><name>PLAY_NEXT</name><value type=\"STRING\"><static>");
	// if (paramBoolean);
	// for (Object localObject3 = "1"; ; localObject3 = "0")
	// {
	// ((StringBuilder)localObject1).append((String)localObject3);
	// ((StringBuilder)localObject1).append("</static></value></param>");
	// if ((paramString != null) && (paramString.length() > 0))
	// {
	// ((StringBuilder)localObject1).append("<param><name>GENRE</name><value type=\"STRING\"><static>");
	// ((StringBuilder)localObject1).append(paramString);
	// ((StringBuilder)localObject1).append("</static></value></param>");
	// }
	// localObject3 = (DirectorDigitalAudio)((Room)localObject2).as();
	// if (localObject3 != null)
	// ((DirectorDigitalAudio)localObject3).a(true);
	// ((Room)localObject2).ag();
	// localObject2 =
	// (SendToDeviceCommand)CommandFactory.SendToDeviceProvider.a();
	// ((SendToDeviceCommand)localObject2).d(false);
	// ((SendToDeviceCommand)localObject2).c(true);
	// ((SendToDeviceCommand)localObject2).c(27);
	// ((SendToDeviceCommand)localObject2).b(100002);
	// ((SendToDeviceCommand)localObject2).a(((StringBuilder)localObject1).toString());
	// ((SendToDeviceCommand)localObject2).c("QUEUE_ALL");
	// boolean bool = this._director.a((Command)localObject2);
	// if (localObject3 != null)
	// ((DirectorDigitalAudio)localObject3).i(true);
	// if (bool)
	// break;
	// ((DirectorDigitalAudio)localObject3).a(false);
	// break;
	// }
	// }
	// }
	// }
	// }
	// catch (Exception k)
	// {
	// Ln.e(localException);
	// k = 0;
	// }
	// while (true)
	// {
	// return k;
	// k = k;
	// }
	// }
	//
	// public Results<Album> aa()
	// {
	// return this.z;
	// }
	//
	// public int ab()
	// {
	// int i;
	// if (this.z == null)
	// i = 0;
	// else
	// i = this.z.h();
	// return i;
	// }
	//
	// public boolean ac()
	// {
	// return this.x;
	// }
	//
	// public void ad()
	// {
	// try
	// {
	// if (this.s != null)
	// this.s.j();
	// this.t = true;
	// return;
	// }
	// catch (Exception localException)
	// {
	// while (true)
	// Ln.e(localException);
	// }
	// }
	//
	// public void ae()
	// {
	// try
	// {
	// if (this.z != null)
	// this.z.j();
	// this.A = true;
	// return;
	// }
	// catch (Exception localException)
	// {
	// while (true)
	// Ln.e(localException);
	// }
	// }
	//
	// public Album b(int paramInt)
	// {
	// Album localAlbum;
	// if (this.z == null)
	// localAlbum = null;
	// else
	// localAlbum = (Album)this.z.c(paramInt);
	// return localAlbum;
	// }
	//
	// public void b(Artist.OnArtistSamplerListener
	// paramOnArtistSamplerListener)
	// {
	// }
	//
	// public void b(Artist.OnArtistTopAlbumsListener
	// paramOnArtistTopAlbumsListener)
	// {
	// }
	//
	// public void b(Artist.OnArtistTopTracksListener
	// paramOnArtistTopTracksListener)
	// {
	// }
	//
	// public void b(Artist.OnArtistUpdateListener paramOnArtistUpdateListener)
	// {
	// if (paramOnArtistUpdateListener != null)
	// {
	// if (this.E == null)
	// this.E = new ArrayList();
	// this.E.add(paramOnArtistUpdateListener);
	// }
	// }
	//
	// public void b(Artist.OnRelatedArtistsListener
	// paramOnRelatedArtistsListener)
	// {
	// }
	//
	// // ERROR //
	// public boolean b(SQLiteDatabase paramSQLiteDatabase)
	// {
	// // Byte code:
	// // 0: aload_1
	// // 1: ifnonnull +7 -> 8
	// // 4: iconst_0
	// // 5: istore_3
	// // 6: iload_3
	// // 7: ireturn
	// // 8: aload_0
	// // 9: invokevirtual 131 com/control4/director/audio/DirectorArtist:au
	// ()Ljava/lang/String;
	// // 12: astore 4
	// // 14: aload 4
	// // 16: ifnull +275 -> 291
	// // 19: aload 4
	// // 21: invokevirtual 57 java/lang/String:length ()I
	// // 24: ifne +6 -> 30
	// // 27: goto +264 -> 291
	// // 30: aload_1
	// // 31: monitorenter
	// // 32: iconst_3
	// // 33: anewarray 53 java/lang/String
	// // 36: astore_2
	// // 37: aload_2
	// // 38: iconst_0
	// // 39: ldc 174
	// // 41: aastore
	// // 42: aload_2
	// // 43: iconst_1
	// // 44: ldc 176
	// // 46: aastore
	// // 47: aload_2
	// // 48: iconst_2
	// // 49: ldc 178
	// // 51: aastore
	// // 52: iconst_1
	// // 53: anewarray 53 java/lang/String
	// // 56: astore_3
	// // 57: aload_3
	// // 58: iconst_0
	// // 59: aload 4
	// // 61: aastore
	// // 62: aload_1
	// // 63: ldc 180
	// // 65: aload_2
	// // 66: ldc_w 426
	// // 69: aload_3
	// // 70: aconst_null
	// // 71: aconst_null
	// // 72: aconst_null
	// // 73: invokevirtual 188 android/database/sqlite/SQLiteDatabase:query
	// (Ljava/lang/String;[Ljava/lang/String;Ljava/lang/String;[Ljava/lang/String;Ljava/lang/String;Ljava/lang/String;Ljava/lang/String;)Landroid/database/Cursor;
	// // 76: astore_2
	// // 77: aload_2
	// // 78: ldc 174
	// // 80: invokeinterface 194 2 0
	// // 85: istore 4
	// // 87: aload_2
	// // 88: ldc 176
	// // 90: invokeinterface 194 2 0
	// // 95: istore 5
	// // 97: aload_2
	// // 98: ldc 178
	// // 100: invokeinterface 194 2 0
	// // 105: istore_3
	// // 106: aload_2
	// // 107: invokeinterface 197 1 0
	// // 112: ifeq +174 -> 286
	// // 115: aload_2
	// // 116: iload 4
	// // 118: invokeinterface 198 2 0
	// // 123: astore 7
	// // 125: aload_2
	// // 126: iload 5
	// // 128: invokeinterface 198 2 0
	// // 133: astore 6
	// // 135: aload_2
	// // 136: iload_3
	// // 137: invokeinterface 198 2 0
	// // 142: astore 8
	// // 144: aload_0
	// // 145: getfield 202 com/control4/director/audio/DirectorArtist:_director
	// Lcom/control4/director/Control4Director;
	// // 148: getfield 208
	// com/control4/director/Control4Director:_albumProvider
	// Lcom/google/inject/aw;
	// // 151: invokeinterface 213 1 0
	// // 156: checkcast 108 com/control4/director/audio/DirectorAlbum
	// // 159: astore 9
	// // 161: aload 7
	// // 163: ifnull +18 -> 181
	// // 166: aload 7
	// // 168: invokevirtual 57 java/lang/String:length ()I
	// // 171: ifle +10 -> 181
	// // 174: aload 9
	// // 176: aload 7
	// // 178: invokevirtual 216 com/control4/director/audio/DirectorAlbum:l
	// (Ljava/lang/String;)V
	// // 181: aload 6
	// // 183: ifnull +18 -> 201
	// // 186: aload 6
	// // 188: invokevirtual 57 java/lang/String:length ()I
	// // 191: ifle +10 -> 201
	// // 194: aload 9
	// // 196: aload 6
	// // 198: invokevirtual 219 com/control4/director/audio/DirectorAlbum:m
	// (Ljava/lang/String;)V
	// // 201: aload 8
	// // 203: ifnull +18 -> 221
	// // 206: aload 8
	// // 208: invokevirtual 57 java/lang/String:length ()I
	// // 211: ifle +10 -> 221
	// // 214: aload 9
	// // 216: aload 8
	// // 218: invokevirtual 222 com/control4/director/audio/DirectorAlbum:n
	// (Ljava/lang/String;)V
	// // 221: aload_0
	// // 222: aload 9
	// // 224: invokevirtual 428 com/control4/director/audio/DirectorArtist:a
	// (Lcom/control4/director/audio/DirectorAlbum;)V
	// // 227: aload_2
	// // 228: invokeinterface 227 1 0
	// // 233: istore 6
	// // 235: iload 6
	// // 237: ifne -122 -> 115
	// // 240: iconst_1
	// // 241: istore_3
	// // 242: aload_2
	// // 243: ifnull +9 -> 252
	// // 246: aload_2
	// // 247: invokeinterface 230 1 0
	// // 252: aload_1
	// // 253: monitorexit
	// // 254: goto -248 -> 6
	// // 257: astore_2
	// // 258: aload_1
	// // 259: monitorexit
	// // 260: aload_2
	// // 261: athrow
	// // 262: astore_2
	// // 263: aload_2
	// // 264: invokestatic 68 roboguice/util/Ln:e (Ljava/lang/Throwable;)I
	// // 267: pop
	// // 268: iconst_0
	// // 269: istore_3
	// // 270: goto -264 -> 6
	// // 273: astore_3
	// // 274: aload_2
	// // 275: ifnull +9 -> 284
	// // 278: aload_2
	// // 279: invokeinterface 230 1 0
	// // 284: aload_3
	// // 285: athrow
	// // 286: iconst_0
	// // 287: istore_3
	// // 288: goto -46 -> 242
	// // 291: iconst_0
	// // 292: istore_3
	// // 293: goto -287 -> 6
	// //
	// // Exception table:
	// // from to target type
	// // 32 106 257 finally
	// // 246 260 257 finally
	// // 278 286 257 finally
	// // 8 32 262 java/lang/Exception
	// // 260 262 262 java/lang/Exception
	// // 106 235 273 finally
	// }
	//
	// public boolean c(SQLiteDatabase paramSQLiteDatabase)
	// {
	// return false;
	// }
	//
	// public Album f(String paramString)
	// {
	// Album localAlbum;
	// if (this.s == null)
	// localAlbum = null;
	// else
	// localAlbum = (Album)this.s.b(paramString);
	// return localAlbum;
	// }
	//
	// public DirectorAudioLibrary f()
	// {
	// try
	// {
	// DirectorAudioLibrary localDirectorAudioLibrary =
	// (DirectorAudioLibrary)this._director.m().s().at();
	// return localDirectorAudioLibrary;
	// }
	// catch (Exception localObject)
	// {
	// while (true)
	// {
	// Ln.e(localException);
	// Object localObject = null;
	// }
	// }
	// }
	//
	// public void g(String paramString)
	// {
	// this.y = paramString;
	// ae();
	// }
	//
	// protected boolean g()
	// {
	// return true;
	// }
	//
	// public Album h(String paramString)
	// {
	// Album localAlbum;
	// if (this.z == null)
	// localAlbum = null;
	// else
	// localAlbum = (Album)this.z.b(paramString);
	// return localAlbum;
	// }
	//
	// public void h()
	// {
	// ad();
	// ae();
	// P();
	// Q();
	// N();
	// O();
	// super.h();
	// }
	//
	// public Channel i()
	// {
	// return null;
	// }
	//
	// public void l(boolean paramBoolean)
	// {
	// this.t = paramBoolean;
	// }
	//
	// public void m(boolean paramBoolean)
	// {
	// this.u = paramBoolean;
	// if (this.w != null)
	// this.w.cancel();
	// if (!this.u)
	// {
	// Iterator localIterator;
	// if (this.E != null)
	// localIterator = this.E.iterator();
	// while (true)
	// {
	// if (!localIterator.hasNext())
	// {
	// this.E.clear();
	// if (this.v == null)
	// break;
	// this.v.cancel();
	// this.v = null;
	// break;
	// }
	// Artist.OnArtistUpdateListener localOnArtistUpdateListener =
	// (Artist.OnArtistUpdateListener)localIterator.next();
	// if (localOnArtistUpdateListener == null)
	// continue;
	// localOnArtistUpdateListener.a(this);
	// }
	// }
	// if (this.v == null)
	// this.v = new Timer();
	// this.w = new DirectorArtist.1(this);
	// this.v.schedule(this.w, 25000L);
	// }
	//
	// public boolean m()
	// {
	// return false;
	// }
	//
	// public void n(boolean paramBoolean)
	// {
	// this.A = paramBoolean;
	// }
	//
	// public boolean n()
	// {
	// return false;
	// }
	//
	// public void o(boolean paramBoolean)
	// {
	// this.B = paramBoolean;
	// if (this.D != null)
	// this.D.cancel();
	// if (!this.B)
	// {
	// Iterator localIterator;
	// if (this.E != null)
	// localIterator = this.E.iterator();
	// while (true)
	// {
	// if (!localIterator.hasNext())
	// {
	// this.E.clear();
	// if (this.C == null)
	// break;
	// this.C.cancel();
	// this.C = null;
	// break;
	// }
	// Artist.OnArtistUpdateListener localOnArtistUpdateListener =
	// (Artist.OnArtistUpdateListener)localIterator.next();
	// if (localOnArtistUpdateListener == null)
	// continue;
	// localOnArtistUpdateListener.a(this, this.y);
	// }
	// }
	// if (this.C == null)
	// this.C = new Timer();
	// this.D = new DirectorArtist.2(this);
	// this.C.schedule(this.D, 25000L);
	// }
	//
	// public void p(boolean paramBoolean)
	// {
	// this.x = paramBoolean;
	// }
	//
	// public Results<Song> r_()
	// {
	// return null;
	// }
	//
	// protected String s_()
	// {
	// return "artist";
	// }
	//
	// public String v()
	// {
	// return null;
	// }
	//
	// public String w()
	// {
	// int i = 0;
	// Object localObject;
	// try
	// {
	// if ((this.y != null) && (this.y.length() > 0))
	// {
	// if (this.z != null)
	// i = this.z.h();
	// String str1 = i + this._context.getString(R.string.albums);
	// }
	// else
	// {
	// int j;
	// if (this.s != null)
	// j = this.s.h();
	// String str2 = j + this._context.getString(R.string.albums);
	// str2 = str2;
	// }
	// }
	// catch (Exception localObject)
	// {
	// Ln.e(localException);
	// localObject = null;
	// }
	// return localObject;
	// }
	//
	// public boolean z()
	// {
	// return false;
	// }
}
