package com.zd.model.audio;

import java.util.ArrayList;
import java.util.Timer;
import java.util.TimerTask;

import android.app.Application;

import com.google.inject.Inject;
import com.zd.model.DirectorResult;
import com.zd.model.DirectorResults;
import com.zd.model.Results;

public class DirectorGenre extends DirectorResult implements Genre {

	@Inject
	private Application _context;
	protected DirectorResults<Artist> a;
	protected volatile boolean b = true;
	protected volatile boolean c = false;
	protected Timer d;
	protected TimerTask e;
	protected boolean f = true;
	protected ArrayList<Genre.OnGenreUpdateListener> g;

	public DirectorGenre() {
		this.H = false;
	}

	public boolean A() {
		return false;
	}

	public boolean B() {
		return false;
	}

	public Results<Artist> C() {
		return null;
	}

	public boolean D() {
		return false;
	}

	public boolean F() {
		return false;
	}

	public Results<Album> G() {
		return null;
	}

	public boolean H() {
		return false;
	}

	public boolean I() {
		return false;
	}

	public boolean J() {
		return false;
	}

	public Results<Song> K() {
		return null;
	}

	public boolean L() {
		return false;
	}

	public boolean M() {
		return false;
	}

	public boolean N() {
		return false;
	}

	public Results<Song> O() {
		return null;
	}

	public boolean P() {
		return false;
	}

	public boolean Q() {
		return false;
	}

	public boolean R() {
		return false;
	}

	public Results<Album> S() {
		return null;
	}

	public boolean T() {
		return false;
	}

	public boolean U() {
		return false;
	}

	public boolean V() {
		return false;
	}

	public Results<Artist> W() {
		return null;
	}

	public boolean X() {
		return false;
	}

	public boolean Y() {
		return false;
	}

	public boolean Z() {
		return false;
	}

	public Artist a(int paramInt) {
		Artist localArtist;
		if (this.a == null)
			localArtist = null;
		else
			localArtist = (Artist) this.a.c(paramInt);
		return localArtist;
	}

	public Artist a(String paramString) {
		Artist localArtist;
		if (this.a == null)
			localArtist = null;
		else
			localArtist = (Artist) this.a.b(paramString);
		return localArtist;
	}

	// public void a(DirectorArtist paramDirectorArtist)
	// {
	// if (paramDirectorArtist == null);
	// while (true)
	// {
	// return;
	// try
	// {
	// String str = paramDirectorArtist.at();
	// if ((str == null) || (str.length() == 0) || (a(str) != null))
	// continue;
	// if (this.a == null)
	// {
	// this.a = new DirectorResults();
	// this.a.a(false);
	// this.a.b(true);
	// this.a.a(au() + " " + this._context.getString(R.string.artists));
	// }
	// this.a.a(paramDirectorArtist);
	// }
	// catch (Exception localException)
	// {
	// Ln.e(localException);
	// }
	// }
	// }
	//
	// public void a(DirectorResult paramDirectorResult)
	// {
	// try
	// {
	// super.a(paramDirectorResult);
	// if ((paramDirectorResult != null) && ((paramDirectorResult instanceof
	// DirectorGenre)))
	// {
	// DirectorGenre localDirectorGenre = (DirectorGenre)paramDirectorResult;
	// DirectorResults localDirectorResults =
	// (DirectorResults)localDirectorGenre.e();
	// if ((localDirectorResults != null) && (localDirectorResults.h() > 0))
	// this.a = localDirectorResults;
	// this.f = localDirectorGenre.g();
	// }
	// }
	// catch (Exception localException)
	// {
	// Ln.e(localException);
	// }
	// }
	//
	// public boolean a(Genre.OnGenreChannelsUpdateListener
	// paramOnGenreChannelsUpdateListener)
	// {
	// return false;
	// }
	//
	// public boolean a(Genre.OnGenreKeyAlbumsUpdateListener
	// paramOnGenreKeyAlbumsUpdateListener)
	// {
	// return false;
	// }
	//
	// public boolean a(Genre.OnGenreKeyArtistsUpdateListener
	// paramOnGenreKeyArtistsUpdateListener)
	// {
	// return false;
	// }
	//
	// public boolean a(Genre.OnGenreNewAlbumsUpdateListener
	// paramOnGenreNewAlbumsUpdateListener)
	// {
	// return false;
	// }
	//
	// public boolean a(Genre.OnGenrePlaylistsUpdateListener
	// paramOnGenrePlaylistsUpdateListener)
	// {
	// return false;
	// }
	//
	// public boolean a(Genre.OnGenreSamplerTracksUpdateListener
	// paramOnGenreSamplerTracksUpdateListener)
	// {
	// return false;
	// }
	//
	// public boolean a(Genre.OnGenreSubGenresUpdateListener
	// paramOnGenreSubGenresUpdateListener)
	// {
	// return false;
	// }
	//
	// public boolean a(Genre.OnGenreTopAlbumsUpdateListener
	// paramOnGenreTopAlbumsUpdateListener)
	// {
	// return false;
	// }
	//
	// public boolean a(Genre.OnGenreTopArtistsUpdateListener
	// paramOnGenreTopArtistsUpdateListener)
	// {
	// return false;
	// }
	//
	// public boolean a(Genre.OnGenreTopTracksUpdateListener
	// paramOnGenreTopTracksUpdateListener)
	// {
	// return false;
	// }
	//
	// public boolean a(Genre.OnGenreUpdateListener paramOnGenreUpdateListener)
	// {
	// boolean bool1 = true;
	// try
	// {
	// if (this._director == null)
	// {
	// bool1 = false;
	// break label200;
	// }
	// if (this.c)
	// break label200;
	// if (this._director.G())
	// {
	// bool1 = b(this._director.q());
	// c(false);
	// d(false);
	// if (paramOnGenreUpdateListener == null)
	// break label200;
	// paramOnGenreUpdateListener.a(this);
	// }
	// }
	// catch (Exception i)
	// {
	// Ln.e(localException);
	// d(false);
	// int i = 0;
	// }
	// d(true);
	// Object localObject = au();
	// if ((localObject != null) && (((String)localObject).length() != 0) &&
	// (!((String)localObject).equals("(Empty)")));
	// while (true)
	// {
	// String str2 = ((String)localObject).replaceAll("&", "&amp;");
	// localObject =
	// (GetGenreArtistsCommand)CommandFactory.GetGenreArtistsProvider.a();
	// ((GetGenreArtistsCommand)localObject).a(str2);
	// ((GetGenreArtistsCommand)localObject).a("genre", this);
	// ((GetGenreArtistsCommand)localObject).a("listener",
	// paramOnGenreUpdateListener);
	// ((GetGenreArtistsCommand)localObject).a("audio-library", d());
	// ((GetGenreArtistsCommand)localObject).b(this._director.m().r());
	// boolean bool2 = this._director.a((Command)localObject);
	// if (!bool2)
	// d(false);
	// label200: return bool2;
	// String str1 = "";
	// }
	// }
	//
	// public Results<Album> aa()
	// {
	// return null;
	// }
	//
	// public boolean ab()
	// {
	// return false;
	// }
	//
	// public boolean ac()
	// {
	// return false;
	// }
	//
	// public boolean ad()
	// {
	// return false;
	// }
	//
	// public Results<Playlist> ae()
	// {
	// return null;
	// }
	//
	// public void af()
	// {
	// }
	//
	// public void ag()
	// {
	// }
	//
	// public void ah()
	// {
	// }
	//
	// public void ai()
	// {
	// }
	//
	// public void aj()
	// {
	// }
	//
	// public void ak()
	// {
	// }
	//
	// public void al()
	// {
	// }
	//
	// public void am()
	// {
	// }
	//
	// public void an()
	// {
	// }
	//
	// public boolean ao()
	// {
	// return false;
	// }
	//
	// public boolean ap()
	// {
	// return false;
	// }
	//
	// public boolean aq()
	// {
	// return false;
	// }
	//
	// public Results<Channel> ar()
	// {
	// return null;
	// }
	//
	// public void as()
	// {
	// }
	//
	// public void b(Genre.OnGenreChannelsUpdateListener
	// paramOnGenreChannelsUpdateListener)
	// {
	// }
	//
	// public void b(Genre.OnGenreKeyAlbumsUpdateListener
	// paramOnGenreKeyAlbumsUpdateListener)
	// {
	// }
	//
	// public void b(Genre.OnGenreKeyArtistsUpdateListener
	// paramOnGenreKeyArtistsUpdateListener)
	// {
	// }
	//
	// public void b(Genre.OnGenreNewAlbumsUpdateListener
	// paramOnGenreNewAlbumsUpdateListener)
	// {
	// }
	//
	// public void b(Genre.OnGenrePlaylistsUpdateListener
	// paramOnGenrePlaylistsUpdateListener)
	// {
	// }
	//
	// public void b(Genre.OnGenreSamplerTracksUpdateListener
	// paramOnGenreSamplerTracksUpdateListener)
	// {
	// }
	//
	// public void b(Genre.OnGenreSubGenresUpdateListener
	// paramOnGenreSubGenresUpdateListener)
	// {
	// }
	//
	// public void b(Genre.OnGenreTopAlbumsUpdateListener
	// paramOnGenreTopAlbumsUpdateListener)
	// {
	// }
	//
	// public void b(Genre.OnGenreTopArtistsUpdateListener
	// paramOnGenreTopArtistsUpdateListener)
	// {
	// }
	//
	// public void b(Genre.OnGenreTopTracksUpdateListener
	// paramOnGenreTopTracksUpdateListener)
	// {
	// }
	//
	// public void b(Genre.OnGenreUpdateListener paramOnGenreUpdateListener)
	// {
	// if (paramOnGenreUpdateListener != null)
	// {
	// if (this.g == null)
	// this.g = new ArrayList();
	// this.g.add(paramOnGenreUpdateListener);
	// }
	// }
	//
	// public boolean b()
	// {
	// return this.b;
	// }
	//
	// // ERROR //
	// public boolean b(android.database.sqlite.SQLiteDatabase
	// paramSQLiteDatabase)
	// {
	// // Byte code:
	// // 0: aload_1
	// // 1: ifnonnull +7 -> 8
	// // 4: iconst_0
	// // 5: istore_3
	// // 6: iload_3
	// // 7: ireturn
	// // 8: aload_1
	// // 9: monitorenter
	// // 10: iconst_1
	// // 11: anewarray 86 java/lang/String
	// // 14: astore_2
	// // 15: aload_2
	// // 16: iconst_0
	// // 17: ldc_w 278
	// // 20: aastore
	// // 21: iconst_1
	// // 22: anewarray 86 java/lang/String
	// // 25: astore_3
	// // 26: aload_3
	// // 27: iconst_0
	// // 28: aload_0
	// // 29: invokevirtual 104 com/control4/director/audio/DirectorGenre:au
	// ()Ljava/lang/String;
	// // 32: aastore
	// // 33: aload_1
	// // 34: ldc_w 280
	// // 37: aload_2
	// // 38: ldc_w 282
	// // 41: aload_3
	// // 42: aconst_null
	// // 43: aconst_null
	// // 44: ldc_w 284
	// // 47: invokevirtual 290 android/database/sqlite/SQLiteDatabase:query
	// (Ljava/lang/String;[Ljava/lang/String;Ljava/lang/String;[Ljava/lang/String;Ljava/lang/String;Ljava/lang/String;Ljava/lang/String;)Landroid/database/Cursor;
	// // 50: astore_2
	// // 51: aload_2
	// // 52: ldc_w 278
	// // 55: invokeinterface 296 2 0
	// // 60: istore_3
	// // 61: aload_2
	// // 62: invokeinterface 299 1 0
	// // 67: ifeq +108 -> 175
	// // 70: aload_2
	// // 71: iload_3
	// // 72: invokeinterface 300 2 0
	// // 77: astore 4
	// // 79: aload_0
	// // 80: getfield 162 com/control4/director/audio/DirectorGenre:_director
	// Lcom/control4/director/Control4Director;
	// // 83: getfield 303
	// com/control4/director/Control4Director:_artistProvider
	// Lcom/google/inject/aw;
	// // 86: invokeinterface 207 1 0
	// // 91: checkcast 80 com/control4/director/audio/DirectorArtist
	// // 94: astore 5
	// // 96: aload 5
	// // 98: aload 4
	// // 100: invokevirtual 306 com/control4/director/audio/DirectorArtist:l
	// (Ljava/lang/String;)V
	// // 103: aload 5
	// // 105: aload 4
	// // 107: invokevirtual 308 com/control4/director/audio/DirectorArtist:m
	// (Ljava/lang/String;)V
	// // 110: aload_0
	// // 111: aload 5
	// // 113: invokevirtual 310 com/control4/director/audio/DirectorGenre:a
	// (Lcom/control4/director/audio/DirectorArtist;)V
	// // 116: aload_2
	// // 117: invokeinterface 313 1 0
	// // 122: istore 4
	// // 124: iload 4
	// // 126: ifne -56 -> 70
	// // 129: iconst_1
	// // 130: istore_3
	// // 131: aload_2
	// // 132: ifnull +9 -> 141
	// // 135: aload_2
	// // 136: invokeinterface 316 1 0
	// // 141: aload_1
	// // 142: monitorexit
	// // 143: goto -137 -> 6
	// // 146: astore_2
	// // 147: aload_1
	// // 148: monitorexit
	// // 149: aload_2
	// // 150: athrow
	// // 151: astore_2
	// // 152: aload_2
	// // 153: invokestatic 137 roboguice/util/Ln:e (Ljava/lang/Throwable;)I
	// // 156: pop
	// // 157: iconst_0
	// // 158: istore_3
	// // 159: goto -153 -> 6
	// // 162: astore_3
	// // 163: aload_2
	// // 164: ifnull +9 -> 173
	// // 167: aload_2
	// // 168: invokeinterface 316 1 0
	// // 173: aload_3
	// // 174: athrow
	// // 175: iconst_0
	// // 176: istore_3
	// // 177: goto -46 -> 131
	// //
	// // Exception table:
	// // from to target type
	// // 10 61 146 finally
	// // 135 149 146 finally
	// // 167 175 146 finally
	// // 8 10 151 java/lang/Exception
	// // 149 151 151 java/lang/Exception
	// // 61 124 162 finally
	// }
	//
	// public void c(boolean paramBoolean)
	// {
	// this.b = paramBoolean;
	// }
	//
	// public boolean c()
	// {
	// return this.c;
	// }
	//
	// protected Object d()
	// {
	// try
	// {
	// AudioLibrary localAudioLibrary = this._director.m().s().at();
	// localAudioLibrary = localAudioLibrary;
	// return localAudioLibrary;
	// }
	// catch (Exception localObject)
	// {
	// while (true)
	// {
	// Ln.e(localException);
	// Object localObject = null;
	// }
	// }
	// }
	//
	// public void d(boolean paramBoolean)
	// {
	// this.c = paramBoolean;
	// if (this.e != null)
	// this.e.cancel();
	// if (!this.c)
	// {
	// Iterator localIterator;
	// if (this.g != null)
	// localIterator = this.g.iterator();
	// while (true)
	// {
	// if (!localIterator.hasNext())
	// {
	// this.g.clear();
	// if (this.d == null)
	// break;
	// this.d.cancel();
	// this.d = null;
	// break;
	// }
	// Genre.OnGenreUpdateListener localOnGenreUpdateListener =
	// (Genre.OnGenreUpdateListener)localIterator.next();
	// if (localOnGenreUpdateListener == null)
	// continue;
	// localOnGenreUpdateListener.a(this);
	// }
	// }
	// if (this.d == null)
	// this.d = new Timer();
	// this.e = new DirectorGenre.1(this);
	// this.d.schedule(this.e, 25000L);
	// }
	//
	// public Results<Artist> e()
	// {
	// return this.a;
	// }
	//
	// public int f()
	// {
	// int i;
	// if (this.a == null)
	// i = 0;
	// else
	// i = this.a.h();
	// return i;
	// }
	//
	// public boolean g()
	// {
	// return this.f;
	// }
	//
	// public void h()
	// {
	// try
	// {
	// super.h();
	// if (this.a != null)
	// this.a.j();
	// this.b = true;
	// ak();
	// al();
	// am();
	// an();
	// aj();
	// af();
	// ah();
	// ag();
	// ai();
	// as();
	// return;
	// }
	// catch (Exception localException)
	// {
	// while (true)
	// Ln.e(localException);
	// }
	// }
	//
	// public boolean i()
	// {
	// return false;
	// }
	//
	// public boolean l()
	// {
	// return false;
	// }
	//
	// public boolean m()
	// {
	// return false;
	// }
	//
	// public Results<Genre> n()
	// {
	// return null;
	// }
	//
	// protected String s_()
	// {
	// return "genre";
	// }
	//
	// public boolean u_()
	// {
	// return false;
	// }
	//
	// public String w()
	// {
	// String str = null;
	// try
	// {
	// if ((this.a != null) && (this.a.h() > 0))
	// {
	// StringBuilder localStringBuilder = new StringBuilder(this.a.h());
	// localStringBuilder.append(" ");
	// localStringBuilder.append(this._context.getString(R.string.artists));
	// str = localStringBuilder.toString();
	// str = str;
	// }
	// return str;
	// }
	// catch (Exception localException)
	// {
	// while (true)
	// Ln.e(localException);
	// }
	// }

	public boolean z() {
		return false;
	}

	@Override
	public boolean a(
			OnGenreChannelsUpdateListener paramOnGenreChannelsUpdateListener) {
		// TODO Auto-generated method stub
		return false;
	}

	@Override
	public boolean a(
			OnGenreKeyAlbumsUpdateListener paramOnGenreKeyAlbumsUpdateListener) {
		// TODO Auto-generated method stub
		return false;
	}

	@Override
	public boolean a(
			OnGenreKeyArtistsUpdateListener paramOnGenreKeyArtistsUpdateListener) {
		// TODO Auto-generated method stub
		return false;
	}

	@Override
	public boolean a(
			OnGenreNewAlbumsUpdateListener paramOnGenreNewAlbumsUpdateListener) {
		// TODO Auto-generated method stub
		return false;
	}

	@Override
	public boolean a(
			OnGenrePlaylistsUpdateListener paramOnGenrePlaylistsUpdateListener) {
		// TODO Auto-generated method stub
		return false;
	}

	@Override
	public boolean a(
			OnGenreSamplerTracksUpdateListener paramOnGenreSamplerTracksUpdateListener) {
		// TODO Auto-generated method stub
		return false;
	}

	@Override
	public boolean a(
			OnGenreSubGenresUpdateListener paramOnGenreSubGenresUpdateListener) {
		// TODO Auto-generated method stub
		return false;
	}

	@Override
	public boolean a(
			OnGenreTopAlbumsUpdateListener paramOnGenreTopAlbumsUpdateListener) {
		// TODO Auto-generated method stub
		return false;
	}

	@Override
	public boolean a(
			OnGenreTopArtistsUpdateListener paramOnGenreTopArtistsUpdateListener) {
		// TODO Auto-generated method stub
		return false;
	}

	@Override
	public boolean a(
			OnGenreTopTracksUpdateListener paramOnGenreTopTracksUpdateListener) {
		// TODO Auto-generated method stub
		return false;
	}

	@Override
	public boolean a(OnGenreUpdateListener paramOnGenreUpdateListener) {
		// TODO Auto-generated method stub
		return false;
	}

	@Override
	public Results<Album> aa() {
		// TODO Auto-generated method stub
		return null;
	}

	@Override
	public boolean ab() {
		// TODO Auto-generated method stub
		return false;
	}

	@Override
	public boolean ac() {
		// TODO Auto-generated method stub
		return false;
	}

	@Override
	public boolean ad() {
		// TODO Auto-generated method stub
		return false;
	}

	@Override
	public Results<Playlist> ae() {
		// TODO Auto-generated method stub
		return null;
	}

	@Override
	public void af() {
		// TODO Auto-generated method stub

	}

	@Override
	public void ag() {
		// TODO Auto-generated method stub

	}

	@Override
	public void ah() {
		// TODO Auto-generated method stub

	}

	@Override
	public void ai() {
		// TODO Auto-generated method stub

	}

	@Override
	public void aj() {
		// TODO Auto-generated method stub

	}

	@Override
	public void ak() {
		// TODO Auto-generated method stub

	}

	@Override
	public void al() {
		// TODO Auto-generated method stub

	}

	@Override
	public void am() {
		// TODO Auto-generated method stub

	}

	@Override
	public void an() {
		// TODO Auto-generated method stub

	}

	@Override
	public boolean ao() {
		// TODO Auto-generated method stub
		return false;
	}

	@Override
	public boolean ap() {
		// TODO Auto-generated method stub
		return false;
	}

	@Override
	public boolean aq() {
		// TODO Auto-generated method stub
		return false;
	}

	@Override
	public Results<Channel> ar() {
		// TODO Auto-generated method stub
		return null;
	}

	@Override
	public void as() {
		// TODO Auto-generated method stub

	}

	@Override
	public void b(
			OnGenreChannelsUpdateListener paramOnGenreChannelsUpdateListener) {
		// TODO Auto-generated method stub

	}

	@Override
	public void b(
			OnGenreKeyAlbumsUpdateListener paramOnGenreKeyAlbumsUpdateListener) {
		// TODO Auto-generated method stub

	}

	@Override
	public void b(
			OnGenreKeyArtistsUpdateListener paramOnGenreKeyArtistsUpdateListener) {
		// TODO Auto-generated method stub

	}

	@Override
	public void b(
			OnGenreNewAlbumsUpdateListener paramOnGenreNewAlbumsUpdateListener) {
		// TODO Auto-generated method stub

	}

	@Override
	public void b(
			OnGenrePlaylistsUpdateListener paramOnGenrePlaylistsUpdateListener) {
		// TODO Auto-generated method stub

	}

	@Override
	public void b(
			OnGenreSamplerTracksUpdateListener paramOnGenreSamplerTracksUpdateListener) {
		// TODO Auto-generated method stub

	}

	@Override
	public void b(
			OnGenreSubGenresUpdateListener paramOnGenreSubGenresUpdateListener) {
		// TODO Auto-generated method stub

	}

	@Override
	public void b(
			OnGenreTopAlbumsUpdateListener paramOnGenreTopAlbumsUpdateListener) {
		// TODO Auto-generated method stub

	}

	@Override
	public void b(
			OnGenreTopArtistsUpdateListener paramOnGenreTopArtistsUpdateListener) {
		// TODO Auto-generated method stub

	}

	@Override
	public void b(
			OnGenreTopTracksUpdateListener paramOnGenreTopTracksUpdateListener) {
		// TODO Auto-generated method stub

	}

	@Override
	public void b(OnGenreUpdateListener paramOnGenreUpdateListener) {
		// TODO Auto-generated method stub

	}

	@Override
	public boolean b() {
		// TODO Auto-generated method stub
		return false;
	}

	@Override
	public boolean c() {
		// TODO Auto-generated method stub
		return false;
	}

	@Override
	public Results<Artist> e() {
		// TODO Auto-generated method stub
		return null;
	}

	@Override
	public int f() {
		// TODO Auto-generated method stub
		return 0;
	}

	@Override
	public boolean g() {
		// TODO Auto-generated method stub
		return false;
	}

	@Override
	public boolean i() {
		// TODO Auto-generated method stub
		return false;
	}

	@Override
	public boolean l() {
		// TODO Auto-generated method stub
		return false;
	}

	@Override
	public boolean m() {
		// TODO Auto-generated method stub
		return false;
	}

	@Override
	public Results<Genre> n() {
		// TODO Auto-generated method stub
		return null;
	}

	@Override
	public boolean u_() {
		// TODO Auto-generated method stub
		return false;
	}
}
